slim_common_robot/__init__.py
slim_common_robot/python_helper_files/__init__.py
slim_common_robot/python_helper_files/account_helper.py
slim_common_robot/python_helper_files/file_helper.py
slim_common_robot/snaplogic_apis_keywords/__init__.py
slim_common_robot/snaplogic_apis_keywords/snaplogic_apis.resource
slim_common_robot/snaplogic_apis_keywords/snaplogic_keywords.resource
slim_common_robot/test_data/__init__.py
slim_common_robot/test_data/slim_groundplex.json
slim_common_robot/test_data/triggered.json
slim_common_robot-2025.4.5.82.195322.dist-info/METADATA
slim_common_robot-2025.4.5.82.195322.dist-info/WHEEL
slim_common_robot-2025.4.5.82.195322.dist-info/top_level.txt
slim_common_robot-2025.4.5.82.195322.dist-info/RECORD
